senile/__init__.py
senile/__main__.py
senile/database.py
senile/icons.py
senile/todo.py
senile-0.3.3.dist-info/AUTHORS
senile-0.3.3.dist-info/LICENSE
senile-0.3.3.dist-info/METADATA
senile-0.3.3.dist-info/WHEEL
senile-0.3.3.dist-info/entry_points.txt
senile-0.3.3.dist-info/top_level.txt
senile-0.3.3.dist-info/RECORD
