Metadata-Version: 2.1
Name: senile
Version: 0.3.3
Summary: A command-line todo utility.
Home-page: https://gitlab.com/nul.one/senile
Author: Predrag Mandic
Author-email: predrag@nul.one
License: BSD
Download-URL: https://gitlab.com/nul.one/senile/-/archive/0.3.3/senile-0.3.3.tar.gz
Platform: UNKNOWN
Classifier: Development Status :: 4 - Beta
Classifier: Environment :: Console
Classifier: License :: OSI Approved :: BSD License
Classifier: Natural Language :: English
Classifier: Operating System :: POSIX :: Linux
Classifier: Programming Language :: Python :: 3 :: Only
Classifier: Topic :: Utilities
Requires-Python: >=3.4.6
Requires-Dist: click (<8.0,>=6.7)
Requires-Dist: prompt-toolkit (<3.0,>=2.0)
Requires-Dist: texttable (<2.0,>=1.6.2)
